CGAL/CGAL_AABB_tree.py
CGAL/CGAL_Advancing_front_surface_reconstruction.py
CGAL/CGAL_Alpha_shape_2.py
CGAL/CGAL_Box_intersection_d.py
CGAL/CGAL_Convex_hull_2.py
CGAL/CGAL_Convex_hull_3.py
CGAL/CGAL_HalfedgeDS.py
CGAL/CGAL_Interpolation.py
CGAL/CGAL_Kernel.py
CGAL/CGAL_Mesh_2.py
CGAL/CGAL_Mesh_3.py
CGAL/CGAL_Point_set_processing_3.py
CGAL/CGAL_Polygon_mesh_processing.py
CGAL/CGAL_Polyhedron_3.py
CGAL/CGAL_Polyline_simplification_2.py
CGAL/CGAL_Spatial_searching.py
CGAL/CGAL_Triangulation_2.py
CGAL/CGAL_Triangulation_3.py
CGAL/CGAL_Voronoi_diagram_2.py
CGAL/_CGAL_AABB_tree.cpython-36m-darwin.so
CGAL/_CGAL_Advancing_front_surface_reconstruction.cpython-36m-darwin.so
CGAL/_CGAL_Alpha_shape_2.cpython-36m-darwin.so
CGAL/_CGAL_Box_intersection_d.cpython-36m-darwin.so
CGAL/_CGAL_Convex_hull_2.cpython-36m-darwin.so
CGAL/_CGAL_Convex_hull_3.cpython-36m-darwin.so
CGAL/_CGAL_HalfedgeDS.cpython-36m-darwin.so
CGAL/_CGAL_Interpolation.cpython-36m-darwin.so
CGAL/_CGAL_Kernel.cpython-36m-darwin.so
CGAL/_CGAL_Mesh_2.cpython-36m-darwin.so
CGAL/_CGAL_Mesh_3.cpython-36m-darwin.so
CGAL/_CGAL_Point_set_processing_3.cpython-36m-darwin.so
CGAL/_CGAL_Polygon_mesh_processing.cpython-36m-darwin.so
CGAL/_CGAL_Polyhedron_3.cpython-36m-darwin.so
CGAL/_CGAL_Polyline_simplification_2.cpython-36m-darwin.so
CGAL/_CGAL_Spatial_searching.cpython-36m-darwin.so
CGAL/_CGAL_Triangulation_2.cpython-36m-darwin.so
CGAL/_CGAL_Triangulation_3.cpython-36m-darwin.so
CGAL/_CGAL_Voronoi_diagram_2.cpython-36m-darwin.so
CGAL/__init__.py
cgal_bindings-1.2.dist-info/DESCRIPTION.rst
cgal_bindings-1.2.dist-info/METADATA
cgal_bindings-1.2.dist-info/RECORD
cgal_bindings-1.2.dist-info/WHEEL
cgal_bindings-1.2.dist-info/metadata.json
cgal_bindings-1.2.dist-info/top_level.txt
