Metadata-Version: 2.0
Name: cgal-bindings
Version: 1.2
Summary: Uses SWIG to generate bindings so you can use certain CGAL classes in Python.
Home-page: https://github.com/sciencectn/cgal-bindings
Author: Chris Taylor
Author-email: sciencectn@gmail.com
License: UNKNOWN
Keywords: cgal computational geometry
Platform: UNKNOWN
Classifier: Intended Audience :: Developers
Classifier: Intended Audience :: Science/Research
Classifier: Programming Language :: Python
Classifier: Topic :: Scientific/Engineering :: GIS
Classifier: Topic :: Scientific/Engineering :: Mathematics
Classifier: Operating System :: POSIX
Classifier: Operating System :: Unix
Classifier: Operating System :: MacOS
Classifier: Programming Language :: Python :: 2.7
